LICENSE
README.md
setup.cfg
setup.py
pywhatsminer/__init__.py
pywhatsminer/beacon.py
pywhatsminer/client.py
pywhatsminer.egg-info/PKG-INFO
pywhatsminer.egg-info/SOURCES.txt
pywhatsminer.egg-info/dependency_links.txt
pywhatsminer.egg-info/requires.txt
pywhatsminer.egg-info/top_level.txt
pywhatsminer/core/__init__.py
pywhatsminer/core/api.py
pywhatsminer/core/exceptions.py
pywhatsminer/core/models.py
pywhatsminer/core/utils.py
pywhatsminer/core/methods/__init__.py
pywhatsminer/core/methods/config.py
pywhatsminer/core/methods/power.py
pywhatsminer/core/methods/system.py